[
  {
    "id": 1,
    "billNumber": "A05254",
    "title": "Enacts the 'New York open water da...",
    "status": "Introduced",
    "committee": "Environmental Conservation",
    "lastAction": "05/29/2025"
  },
  {
    "id": 2,
    "billNumber": "A06452",
    "title": "Requires the superintendent of state...",
    "status": "Introduced",
    "committee": "Education",
    "lastAction": "05/29/2025"
  },
  {
    "id": 3,
    "billNumber": "S03124",
    "title": "Establishes the clean energy workforce...",
    "status": "In Committee",
    "committee": "Energy and Telecommunications",
    "lastAction": "05/28/2025"
  },
  {
    "id": 4,
    "billNumber": "A07891",
    "title": "Relates to mental health services for...",
    "status": "Passed Assembly",
    "committee": "Health",
    "lastAction": "05/27/2025"
  },
  {
    "id": 5,
    "billNumber": "S04567",
    "title": "Amends the vehicle and traffic law...",
    "status": "In Committee",
    "committee": "Transportation",
    "lastAction": "05/26/2025"
  },
  {
    "id": 6,
    "billNumber": "A08234",
    "title": "Relates to affordable housing development...",
    "status": "Introduced",
    "committee": "Housing",
    "lastAction": "05/25/2025"
  },
  {
    "id": 7,
    "billNumber": "S05678",
    "title": "Establishes cybersecurity standards for...",
    "status": "Passed Senate",
    "committee": "Internet and Technology",
    "lastAction": "05/24/2025"
  },
  {
    "id": 8,
    "billNumber": "A09123",
    "title": "Relates to workers' compensation benefits...",
    "status": "In Committee",
    "committee": "Labor",
    "lastAction": "05/23/2025"
  }
]